.bumpversion
.gitignore
MANIFEST.in
README.rst
requirements.txt
setup.cfg
setup.py
tox.ini
pyflash/__init__.py
pyflash/__main__.py
pyflash/cli.py
pyflash/core.py
pyflash/utils.py
pyflash.egg-info/PKG-INFO
pyflash.egg-info/SOURCES.txt
pyflash.egg-info/dependency_links.txt
pyflash.egg-info/entry_points.txt
pyflash.egg-info/not-zip-safe
pyflash.egg-info/requires.txt
pyflash.egg-info/top_level.txt
tests/__init__.py
tests/test_cli.py