Metadata-Version: 2.1
Name: pyflash
Version: 0.3.1
Summary: Get flash like superpowers by automating everyday tasks!
Home-page: https://github.com/chillaranand/pyflash
Author: Chillar Anand
Author-email: anand21nanda@gmail.com
License: BSD
Platform: any
Classifier: Development Status :: 4 - Beta
Classifier: Environment :: Console
Classifier: Intended Audience :: Developers
Classifier: License :: OSI Approved :: BSD License
Classifier: Operating System :: POSIX
Classifier: Operating System :: MacOS
Classifier: Operating System :: Unix
Classifier: Programming Language :: Python
Classifier: Programming Language :: Python :: 3
Classifier: Topic :: Software Development :: Libraries :: Python Modules
